libkeepass/__init__.py
libkeepass/common.py
libkeepass/crypto.py
libkeepass/hbio.py
libkeepass/kdb3.py
libkeepass/kdb4.py
libkeepass/pytwofish.py
libkeepass/twofish.py
libkeepass/utils/__init__.py
libkeepass/utils/check.py
libkeepass/utils/convert.py
libkeepass/utils/merge.py
libkeepass-0.3.1.post1.dist-info/LICENSE.txt
libkeepass-0.3.1.post1.dist-info/METADATA
libkeepass-0.3.1.post1.dist-info/WHEEL
libkeepass-0.3.1.post1.dist-info/pbr.json
libkeepass-0.3.1.post1.dist-info/top_level.txt
libkeepass-0.3.1.post1.dist-info/RECORD
