Metadata-Version: 2.1
Name: libkeepass
Version: 0.3.1.post1
Summary: A library to access KeePass 1.x/KeePassX (v3) and KeePass 2.x (v4) files
Home-page: https://github.com/phpwutz/libkeepass
Author: Lukas Koell
Author-email: phpwutz@gmail.com
License: GPL
Keywords: keepass library
Platform: UNKNOWN
Classifier: Development Status :: 3 - Alpha
Classifier: Programming Language :: Python :: 2.7
Classifier: Programming Language :: Python :: 3.2
Classifier: Programming Language :: Python :: 3.3
Requires-Dist: lxml (>=3.2.1)
Requires-Dist: pycryptodome (>=3.4.11)
Requires-Dist: colorama (>=0.3.2)
